{"name":"Mycelial Communications","body":"## Welcome to Mycelial Communications\r\nWe Provides analysis, design and systems integration consulting services for organizations that are implementing secure communication strategies.  \r\n\r\nOur complete solutions have proven reliability, and set the standard for todays high security voice and video communication.  We pride ourselves in our flexibility and agile development procedures, customizing our software to fit your needs.\r\n\r\n## We want to work with you on\r\n* Secure communication strategies\r\n* High performance telephony systems\r\n* Public telephony networks\r\n* Cellular encryption systems\r\n\r\n## Please contact us for more information\r\nToll free: 888-888-88888\r\n\r\nBy Email: support@mycelialcomm.net\r\n","google":"","note":"Don't delete this file! It's used internally to help with page regeneration.","tagline":""}